{
    "itemsPerContainer": 0,
    "category": "CT_space",
    "craftedObjectTemplate": "object/tangible/ship/crafted/armor/experimental_armor.iff",
    "slots": [
        {
            "optional": false,
            "name": [
                "craft_item_ingredients_n",
                "ship_skin"
            ],
            "options": [
                {
                    "ingredientType": "IT_resourceClass",
                    "ingredients": [
                        {
                            "name": [
                                "craft_item_ingredients_n",
                                "ship_skin"
                            ],
                            "ingredient": "aluminum",
                            "count": 1250
                        }
                    ],
                    "complexity": 0,
                    "skillCommand": "unskilled"
                }
            ],
            "optionalSkillCommand": "",
            "complexity": 0,
            "appearance": ""
        },
        {
            "optional": false,
            "name": [
                "craft_item_ingredients_n",
                "steel_frame"
            ],
            "options": [
                {
                    "ingredientType": "IT_resourceClass",
                    "ingredients": [
                        {
                            "name": [
                                "craft_item_ingredients_n",
                                "steel_frame"
                            ],
                            "ingredient": "steel",
                            "count": 1250
                        }
                    ],
                    "complexity": 0,
                    "skillCommand": "unskilled"
                }
            ],
            "optionalSkillCommand": "",
            "complexity": 0,
            "appearance": ""
        },
        {
            "optional": true,
            "name": [
                "craft_item_ingredients_n",
                "armor_upgrade"
            ],
            "options": [
                {
                    "ingredientType": "IT_templateGeneric",
                    "ingredients": [
                        {
                            "name": [
                                "craft_item_ingredients_n",
                                "armor_upgrade"
                            ],
                            "ingredient": "object/tangible/ship/crafted/armor/base_armor_subcomponent_mk5.iff",
                            "count": 1
                        }
                    ],
                    "complexity": 0,
                    "skillCommand": "unskilled"
                }
            ],
            "optionalSkillCommand": "",
            "complexity": 0,
            "appearance": ""
        },
        {
            "optional": false,
            "name": [
                "craft_item_ingredients_n",
                "absorptive_layer"
            ],
            "options": [
                {
                    "ingredientType": "IT_resourceClass",
                    "ingredients": [
                        {
                            "name": [
                                "craft_item_ingredients_n",
                                "absorptive_layer"
                            ],
                            "ingredient": "ore",
                            "count": 1250
                        }
                    ],
                    "complexity": 0,
                    "skillCommand": "unskilled"
                }
            ],
            "optionalSkillCommand": "",
            "complexity": 0,
            "appearance": ""
        },
        {
            "optional": false,
            "name": [
                "craft_item_ingredients_n",
                "plate_lubricant"
            ],
            "options": [
                {
                    "ingredientType": "IT_resourceClass",
                    "ingredients": [
                        {
                            "name": [
                                "craft_item_ingredients_n",
                                "plate_lubricant"
                            ],
                            "ingredient": "petrochem_inert",
                            "count": 1250
                        }
                    ],
                    "complexity": 0,
                    "skillCommand": "unskilled"
                }
            ],
            "optionalSkillCommand": "",
            "complexity": 0,
            "appearance": ""
        }
    ],
    "skillCommands": [
        "unskilled"
    ],
    "manufactureScripts": [
        "systems.crafting.space.armor.crafting_basic_armor"
    ],
    "xpPoints": [
        {
            "type": "XP_shipwright",
            "level": 0,
            "value": 0
        }
    ],
    "complexity": 36,
    "sharedTemplate": "object/draft_schematic/space/armor/shared_exp_durasteel_plating.iff",
    "volume": 1
}