{
    "parent": "object/draft_schematic/dance_prop/prop_base.iff",
    "itemsPerContainer": 25,
    "craftedObjectTemplate": "object/tangible/dance_prop/prop_ribbon_spark_l.iff",
    "slots": [
        {
            "optional": false,
            "name": [
                "craft_furniture_ingredients_n",
                "handle"
            ],
            "options": [
                {
                    "ingredientType": "IT_resourceClass",
                    "ingredients": [
                        {
                            "name": [
                                "craft_furniture_ingredients_n",
                                "handle"
                            ],
                            "ingredient": "organic",
                            "count": 15
                        }
                    ],
                    "complexity": 0,
                    "skillCommand": "unskilled"
                }
            ],
            "optionalSkillCommand": "",
            "complexity": 0,
            "appearance": ""
        },
        {
            "optional": false,
            "name": [
                "craft_furniture_ingredients_n",
                "ribbon"
            ],
            "options": [
                {
                    "ingredientType": "IT_resourceClass",
                    "ingredients": [
                        {
                            "name": [
                                "craft_furniture_ingredients_n",
                                "ribbon"
                            ],
                            "ingredient": "fiberplast",
                            "count": 25
                        }
                    ],
                    "complexity": 0,
                    "skillCommand": "unskilled"
                }
            ],
            "optionalSkillCommand": "",
            "complexity": 0,
            "appearance": ""
        },
        {
            "optional": false,
            "name": [
                "craft_furniture_ingredients_n",
                "metal_powder"
            ],
            "options": [
                {
                    "ingredientType": "IT_resourceClass",
                    "ingredients": [
                        {
                            "name": [
                                "craft_furniture_ingredients_n",
                                "metal_powder"
                            ],
                            "ingredient": "metal",
                            "count": 10
                        }
                    ],
                    "complexity": 0,
                    "skillCommand": "unskilled"
                }
            ],
            "optionalSkillCommand": "",
            "complexity": 0,
            "appearance": ""
        }
    ],
    "skillCommands": [
        "unskilled"
    ],
    "complexity": 11,
    "sharedTemplate": "object/draft_schematic/dance_prop/shared_prop_ribbon_spark_l.iff",
    "volume": 1
}