{
    "itemsPerContainer": 25,
    "craftedObjectTemplate": "object/tangible/component/droid/performer_effects_d.iff",
    "slots": [
        {
            "optional": false,
            "name": [
                "craft_droid_ingredients_n",
                "module_frame"
            ],
            "options": [
                {
                    "ingredientType": "IT_resourceClass",
                    "ingredients": [
                        {
                            "name": [
                                "craft_droid_ingredients_n",
                                "module_frame"
                            ],
                            "ingredient": "steel",
                            "count": 40
                        }
                    ],
                    "complexity": 0,
                    "skillCommand": "unskilled"
                }
            ],
            "optionalSkillCommand": "",
            "complexity": 0,
            "appearance": ""
        },
        {
            "optional": false,
            "name": [
                "craft_droid_ingredients_n",
                "data_storage_matrix"
            ],
            "options": [
                {
                    "ingredientType": "IT_resourceClass",
                    "ingredients": [
                        {
                            "name": [
                                "craft_droid_ingredients_n",
                                "data_storage_matrix"
                            ],
                            "ingredient": "gas_inert",
                            "count": 20
                        }
                    ],
                    "complexity": 0,
                    "skillCommand": "unskilled"
                }
            ],
            "optionalSkillCommand": "",
            "complexity": 0,
            "appearance": ""
        },
        {
            "optional": false,
            "name": [
                "craft_droid_ingredients_n",
                "light_crystals"
            ],
            "options": [
                {
                    "ingredientType": "IT_resourceClass",
                    "ingredients": [
                        {
                            "name": [
                                "craft_droid_ingredients_n",
                                "light_crystals"
                            ],
                            "ingredient": "gemstone_crystalline",
                            "count": 60
                        }
                    ],
                    "complexity": 0,
                    "skillCommand": "unskilled"
                }
            ],
            "optionalSkillCommand": "",
            "complexity": 0,
            "appearance": ""
        }
    ],
    "skillCommands": [
        "unskilled"
    ],
    "manufactureScripts": [
        "systems.crafting.droid.crafted_items.crafting_droid_components"
    ],
    "complexity": 21,
    "sharedTemplate": "object/draft_schematic/droid/component/shared_performer_effects_d.iff",
    "volume": 1
}