{
    "itemsPerContainer": 0,
    "craftedObjectTemplate": "object/tangible/furniture/all/frn_all_camp_lantern_s3.iff",
    "slots": [
        {
            "optional": false,
            "name": [
                "craft_furniture_ingredients_n",
                "lamp_body"
            ],
            "options": [
                {
                    "ingredientType": "IT_resourceClass",
                    "ingredients": [
                        {
                            "name": [
                                "craft_furniture_ingredients_n",
                                "lamp_body"
                            ],
                            "ingredient": "metal",
                            "count": 80
                        }
                    ],
                    "complexity": 0,
                    "skillCommand": "unskilled"
                }
            ],
            "optionalSkillCommand": "",
            "complexity": 0,
            "appearance": ""
        },
        {
            "optional": false,
            "name": [
                "craft_furniture_ingredients_n",
                "lamp_assembly"
            ],
            "options": [
                {
                    "ingredientType": "IT_resourceClass",
                    "ingredients": [
                        {
                            "name": [
                                "craft_furniture_ingredients_n",
                                "lamp_assembly"
                            ],
                            "ingredient": "metal",
                            "count": 25
                        }
                    ],
                    "complexity": 0,
                    "skillCommand": "unskilled"
                }
            ],
            "optionalSkillCommand": "",
            "complexity": 0,
            "appearance": ""
        },
        {
            "optional": false,
            "name": [
                "craft_furniture_ingredients_n",
                "globe"
            ],
            "options": [
                {
                    "ingredientType": "IT_resourceClass",
                    "ingredients": [
                        {
                            "name": [
                                "craft_furniture_ingredients_n",
                                "globe"
                            ],
                            "ingredient": "gemstone",
                            "count": 60
                        }
                    ],
                    "complexity": 0,
                    "skillCommand": "unskilled"
                }
            ],
            "optionalSkillCommand": "",
            "complexity": 0,
            "appearance": ""
        },
        {
            "optional": false,
            "name": [
                "craft_furniture_ingredients_n",
                "filament"
            ],
            "options": [
                {
                    "ingredientType": "IT_resourceClass",
                    "ingredients": [
                        {
                            "name": [
                                "craft_furniture_ingredients_n",
                                "filament"
                            ],
                            "ingredient": "aluminum",
                            "count": 15
                        }
                    ],
                    "complexity": 0,
                    "skillCommand": "unskilled"
                }
            ],
            "optionalSkillCommand": "",
            "complexity": 0,
            "appearance": ""
        }
    ],
    "skillCommands": [
        "unskilled"
    ],
    "manufactureScripts": [
        "systems.crafting.furniture.specific_item.furniture_lamp"
    ],
    "complexity": 30,
    "sharedTemplate": "object/draft_schematic/furniture/shared_furniture_meatlump_camping_light_02.iff",
    "volume": 1
}