{
    "itemsPerContainer": 25,
    "craftedObjectTemplate": "object/tangible/food/crafted/dish_fire_stew.iff",
    "slots": [
        {
            "optional": false,
            "name": [
                "craft_food_ingredients_n",
                "water"
            ],
            "options": [
                {
                    "ingredientType": "IT_resourceClass",
                    "ingredients": [
                        {
                            "name": [
                                "craft_food_ingredients_n",
                                "water"
                            ],
                            "ingredient": "water",
                            "count": 10
                        }
                    ],
                    "complexity": 0,
                    "skillCommand": "unskilled"
                }
            ],
            "optionalSkillCommand": "",
            "complexity": 0,
            "appearance": ""
        },
        {
            "optional": false,
            "name": [
                "craft_food_ingredients_n",
                "base"
            ],
            "options": [
                {
                    "ingredientType": "IT_resourceClass",
                    "ingredients": [
                        {
                            "name": [
                                "craft_food_ingredients_n",
                                "base"
                            ],
                            "ingredient": "meat",
                            "count": 10
                        }
                    ],
                    "complexity": 0,
                    "skillCommand": "unskilled"
                }
            ],
            "optionalSkillCommand": "",
            "complexity": 0,
            "appearance": ""
        },
        {
            "optional": false,
            "name": [
                "craft_food_ingredients_n",
                "desert_seasoning"
            ],
            "options": [
                {
                    "ingredientType": "IT_resourceClass",
                    "ingredients": [
                        {
                            "name": [
                                "craft_food_ingredients_n",
                                "desert_seasoning"
                            ],
                            "ingredient": "fruit_flowers",
                            "count": 5
                        }
                    ],
                    "complexity": 0,
                    "skillCommand": "unskilled"
                }
            ],
            "optionalSkillCommand": "",
            "complexity": 0,
            "appearance": ""
        },
        {
            "optional": false,
            "name": [
                "craft_food_ingredients_n",
                "puk"
            ],
            "options": [
                {
                    "ingredientType": "IT_template",
                    "ingredients": [
                        {
                            "name": [
                                "craft_food_ingredients_n",
                                "puk"
                            ],
                            "ingredient": "object/tangible/food/crafted/dish_puk.iff",
                            "count": 1
                        }
                    ],
                    "complexity": 0,
                    "skillCommand": "unskilled"
                }
            ],
            "optionalSkillCommand": "",
            "complexity": 0,
            "appearance": ""
        }
    ],
    "skillCommands": [
        "unskilled"
    ],
    "manufactureScripts": [
        "systems.crafting.food.crafted_items.crafting_chef_meal_food"
    ],
    "complexity": 16,
    "sharedTemplate": "object/draft_schematic/food/shared_dish_fire_stew.iff",
    "volume": 1
}